peakqc/__init__.py
peakqc/_version.py
peakqc/fld_scoring.py
peakqc/general.py
peakqc/insertsizes.py
peakqc-0.1.3.dist-info/licenses/LICENSE
peakqc-0.1.3.dist-info/METADATA
peakqc-0.1.3.dist-info/WHEEL
peakqc-0.1.3.dist-info/top_level.txt
peakqc-0.1.3.dist-info/RECORD
